LICENSE.txt
MANIFEST.in
README.rst
requirements.txt
setup.cfg
setup.py
versioneer.py
./EPIC/_version.py
EPIC/LCDM.ini
EPIC/__init__.py
EPIC/_version.py
EPIC/cde_testing.py
EPIC/epic.py
EPIC/sim_objects.py
EPIC/cosmology/EoS_parametrizations.py
EPIC/cosmology/__init__.py
EPIC/cosmology/available_species.ini
EPIC/cosmology/cosmic_objects.py
EPIC/cosmology/default_parameter_flatpriors.ini
EPIC/cosmology/default_parameter_gaussiansigmapriors.ini
EPIC/cosmology/default_parameter_units.ini
EPIC/cosmology/default_parameter_values.ini
EPIC/cosmology/model_recipes.ini
EPIC/cosmology/observations.py
EPIC/cosmology/__pycache__/EoS_parametrizations.cpython-35.pyc
EPIC/cosmology/__pycache__/EoS_parametrizations.cpython-37.pyc
EPIC/cosmology/__pycache__/__init__.cpython-35.pyc
EPIC/cosmology/__pycache__/__init__.cpython-37.pyc
EPIC/cosmology/__pycache__/cosmic_objects.cpython-35.pyc
EPIC/cosmology/__pycache__/cosmic_objects.cpython-37.pyc
EPIC/cosmology/__pycache__/observations.cpython-35.pyc
EPIC/cosmology/__pycache__/observations.cpython-37.pyc
EPIC/cosmology/observational_data/available_observables.ini
EPIC/cosmology/observational_data/conflicting_dataset_pairs.txt
EPIC/cosmology/observational_data/BAO/6dF+SDSS_MGS/data.txt
EPIC/cosmology/observational_data/BAO/6dF+SDSS_MGS/fiducial.p
EPIC/cosmology/observational_data/BAO/SDSS_BOSS_CMASS/corr.txt
EPIC/cosmology/observational_data/BAO/SDSS_BOSS_CMASS/data.txt
EPIC/cosmology/observational_data/BAO/SDSS_BOSS_CMASS/fiducial.p
EPIC/cosmology/observational_data/BAO/SDSS_BOSS_LOWZ/data.txt
EPIC/cosmology/observational_data/BAO/SDSS_BOSS_LOWZ/fiducial.p
EPIC/cosmology/observational_data/BAO/SDSS_BOSS_Lyalpha-Forests/corr.txt
EPIC/cosmology/observational_data/BAO/SDSS_BOSS_Lyalpha-Forests/data.txt
EPIC/cosmology/observational_data/BAO/SDSS_BOSS_QuasarLyman/corr.txt
EPIC/cosmology/observational_data/BAO/SDSS_BOSS_QuasarLyman/data.txt
EPIC/cosmology/observational_data/BAO/SDSS_BOSS_QuasarLyman/fiducial.p
epic_code.egg-info/PKG-INFO
epic_code.egg-info/SOURCES.txt
epic_code.egg-info/dependency_links.txt
epic_code.egg-info/requires.txt
epic_code.egg-info/top_level.txt