Metadata-Version: 1.1
Name: epic-code
Version: 1.4
Summary: Another MCMC sampler for Cosmology
Home-page: https://epic-code.readthedocs.io
Author: Rafael Marcondes
Author-email: rafael.marcondes@outlook.com
License: Copyright (c) 2017, Rafael J. F. Marcondes
